sarban/__init__.py
sarban/sarban.py
sarban/errors/__init__.py
sarban/methods/__init__.py
sarban/methods/base.py
sarban/methods/clients.py
sarban/methods/inbounds.py
sarban/methods/login.py
sarban/sub_gen/__init__.py
sarban-1.1.0.dist-info/LICENSE
sarban-1.1.0.dist-info/METADATA
sarban-1.1.0.dist-info/WHEEL
sarban-1.1.0.dist-info/top_level.txt
sarban-1.1.0.dist-info/RECORD
