Metadata-Version: 2.1
Name: sarban
Version: 1.1.0
Summary: marzban panel API easey-managing.
Home-page: https://github.com/liwyd/sarban
Author: liwyd
License: MIT
Keywords: sarban,marzban,marzban python,marzban panel
Classifier: Programming Language :: Python :: 3
Classifier: License :: OSI Approved :: MIT License
Classifier: Operating System :: OS Independent
Requires-Python: >=3.6
License-File: LICENSE
Requires-Dist: requests
